matp/__init__.py
matp/protocol.py
matp/crypto/__init__.py
matp/crypto/fractal.py
matp/crypto/quantum.py
matp/ghost/__init__.py
matp/ghost/engine.py
matp/ghost/fast_ghost.py
matp/ghost/strategies/__init__.py
matp/ghost/strategies/exif_image.py
matp/ghost/strategies/json_api.py
matp/groups/__init__.py
matp/groups/fractal_ratchet.py
matp/groups/manager.py
matp/mitm/__init__.py
matp/mitm/bloom_filter.py
matp/mitm/connection_pool.py
matp/mitm/flow_fingerprint.py
matp/mitm/lightning.py
matp/mitm/predictive_crypto.py
matp/mitm/stochastic_auth.py
matp/mitm/zkp_path.py
matp/ratchet/__init__.py
matp/ratchet/adaptive.py
matp/ratchet/rclassical.py
matp/zkp/__init__.py
matp/zkp/sigma.py
matp-0.5.2.dist-info/licenses/LICENSE.txt
matp-0.5.2.dist-info/METADATA
matp-0.5.2.dist-info/WHEEL
matp-0.5.2.dist-info/top_level.txt
matp-0.5.2.dist-info/RECORD
