Metadata-Version: 2.4
Name: matp
Version: 0.5.2
Summary: Matryoshka Protocol - Invisible quantum-resistant messaging
Home-page: https://github.com/sangeet01/matp
Author: Sangeet Sharma
Author-email: sangeet.music01@gmail.com
License: Apache-2.0
Project-URL: Homepage, https://github.com/sangeet01/matp
Project-URL: Repository, https://github.com/sangeet01/matp
Keywords: cryptography,steganography,encryption,messaging,security,matp
Classifier: Development Status :: 4 - Beta
Classifier: Intended Audience :: Developers
Classifier: Topic :: Security :: Cryptography
Classifier: License :: OSI Approved :: Apache Software License
Classifier: Programming Language :: Python :: 3
Requires-Python: >=3.9
License-File: LICENSE.txt
Requires-Dist: cryptography>=41.0.0
Requires-Dist: liboqs-python==0.10.0
Dynamic: author-email
Dynamic: home-page
Dynamic: license-file
Dynamic: requires-python
